{
  "orgName": "MetaGame",
  "tokenName": "Seeds Token",
  "tokenSymbol": "SEEDS",
  "ContributionReward": [{}],
  "SchemeRegistrar": [
    {
      "voteRegisterParams": 1,
      "voteRemoveParams": 1
    }
  ],
  "StandAloneContracts": [
    {
      "name": "ContributionRewardExt",
      "fromArc": true,
      "arcVersion": "0.0.1-rc.41"
    },
    {
      "name": "Competition",
      "fromArc": true,
      "params": [{ "StandAloneContract": 0 }],
      "arcVersion": "0.0.1-rc.41"
    }
  ],
  "VotingMachinesParams": [
    {
      "boostedVotePeriodLimit": 86400,
      "daoBountyConst": 10,
      "minimumDaoBounty": 150,
      "queuedVotePeriodLimit": 604800,
      "queuedVoteRequiredPercentage": 50,
      "preBoostedVotePeriodLimit": 86400,
      "proposingRepReward": 0,
      "quietEndingPeriod": 57600,
      "thresholdConst": 2000,
      "voteOnBehalf": "0x0000000000000000000000000000000000000000",
      "votersReputationLossRatio": 0,
      "activationTime": 0
    },
    {
      "boostedVotePeriodLimit": 345600,
      "daoBountyConst": 10,
      "minimumDaoBounty": 400,
      "queuedVotePeriodLimit": 1209600,
      "queuedVoteRequiredPercentage": 50,
      "preBoostedVotePeriodLimit": 345600,
      "proposingRepReward": 0,
      "quietEndingPeriod": 172800,
      "thresholdConst": 2000,
      "voteOnBehalf": "0x0000000000000000000000000000000000000000",
      "votersReputationLossRatio": 0,
      "activationTime": 0
    }
  ],
  "schemes": {
    "ContributionReward": true,
    "SchemeRegistrar": true
  },
  "CustomSchemes": [
    {
      "name": "ContributionRewardExt",
      "schemeName": "ContributionRewardExt",
      "address": { "StandAloneContract": 0 },
      "isUniversal": false,
      "params": [
        "GenesisProtocolAddress",
        { "voteParams": 0 },
        { "StandAloneContract": 1 }
      ],
      "permissions": "0x00000000",
      "alias": "ContributionRewardExt",
      "fromArc": true,
      "arcVersion": "0.0.1-rc.41"
    }
  ],
  "useDaoCreator": true,
  "founders": [
    {
      "address": "0xB53b0255895c4F9E3a185E484e5B674bCCfbc076",
      "tokens": 1727,
      "reputation": 1727
    },
    {
      "address": "0x66b1De0f14a0ce971F7f248415063D44CAF19398",
      "tokens": 297,
      "reputation": 297
    },
    {
      "address": "0x66b1De0f14a0ce971F7f248415063D44CAF19398",
      "tokens": 366,
      "reputation": 366
    },
    {
      "address": "0x28f3EB8BB432d522858a9237350D7aaa54c2c557",
      "tokens": 65,
      "reputation": 65
    },
    {
      "address": "0xa15Ca74e65bf72730811ABF95163E89aD9b9DFF6",
      "tokens": 1,
      "reputation": 1
    }
  ]
}
